pythoncms/.env_demo
pythoncms/.test.prod.env
pythoncms/CHANGELOG.md
pythoncms/__init__.py
pythoncms/app.py
pythoncms/autoapp.py.example
pythoncms/cli.py
pythoncms/config.py
pythoncms/config_demo.json
pythoncms/conftest.py
pythoncms/init.py
pythoncms/manage.py
pythoncms/shopyo_admin.py
pythoncms/wsgi.py.example
pythoncms/__pycache__/__init__.cpython-313.pyc
pythoncms/modules/__init__.py
pythoncms/modules/contact/forms.py
pythoncms/modules/contact/global.py
pythoncms/modules/contact/info.json
pythoncms/modules/contact/models.py
pythoncms/modules/contact/view.py
pythoncms/modules/contact/templates/contact/contact_form.html
pythoncms/modules/contact/templates/contact/dashboard.html
pythoncms/modules/contact/templates/contact/blocks/sidebar.html
pythoncms/modules/contact/tests/test_contact.py
pythoncms/modules/resource/forms.py
pythoncms/modules/resource/info.json
pythoncms/modules/resource/models.py
pythoncms/modules/resource/view.py
pythoncms/modules/resource/templates/resource/blocks/sidebar.html
pythoncms/modules/www/forms.py
pythoncms/modules/www/global.py
pythoncms/modules/www/info.json
pythoncms/modules/www/models.py
pythoncms/modules/www/view.py
pythoncms/modules/www/templates/www/index.html
pythoncms/modules/www/templates/www/blocks/sidebar.html
pythoncms/static/bootstrap-grid.min.css
pythoncms/static/bootstrap-reboot.min.css
pythoncms/static/bootstrap.bundle.min.js
pythoncms/static/bootstrap.min.css
pythoncms/static/box.svg
pythoncms/static/favicon.ico
pythoncms/static/jquery_3.2.1.min.js
pythoncms/static/logo.png
pythoncms/static/logo.svg
pythoncms/static/shopyo.png
pythoncms/static/shopyo.svg
pythoncms/static/css/b4vtabs.min.css
pythoncms/static/css/simple_sidebar.css
pythoncms/static/default/default_product.jpg
pythoncms/static/default/default_subcategory.jpg
pythoncms/static/fontawesome/LICENSE.txt
pythoncms/static/fontawesome/css/all.css
pythoncms/static/fontawesome/css/all.min.css
pythoncms/static/fontawesome/css/brands.css
pythoncms-1.4.2.dist-info/METADATA
pythoncms-1.4.2.dist-info/WHEEL
pythoncms-1.4.2.dist-info/entry_points.txt
pythoncms-1.4.2.dist-info/top_level.txt
pythoncms-1.4.2.dist-info/RECORD
