Metadata-Version: 2.4
Name: pythoncms
Version: 1.4.2
Home-page: 
Author: Abdur-Rahmaan Janhangeer
Author-email: arj.python@gmail.com
Project-URL: Bug Reports, https://github.com/shopyo/pythoncms/issues
Project-URL: Source, https://github.com/shopyo/pythoncms
Keywords: cms
Classifier: Development Status :: 4 - Beta
Classifier: Intended Audience :: Developers
Classifier: License :: OSI Approved :: MIT License
Classifier: Programming Language :: Python :: 3.7
Classifier: Programming Language :: Python :: 3.8
Classifier: Programming Language :: Python :: 3.9
Classifier: Programming Language :: Python :: 3.10
Classifier: Programming Language :: Python :: 3.11
Classifier: Programming Language :: Python :: 3.12
Classifier: Programming Language :: Python :: 3.13
Requires-Python: >=3.7
Requires-Dist: shopyo==4.12.1
Requires-Dist: SQLAlchemy==1.4.46
Requires-Dist: python-dotenv
Requires-Dist: shopyo-appadmin==1.2.0
Requires-Dist: shopyo-auth==1.2.0
Requires-Dist: shopyo-base==1.2.0
Requires-Dist: shopyo-dashboard==1.1.1
Requires-Dist: shopyo-i18n==1.1.0
Requires-Dist: shopyo-page==1.2.0
Requires-Dist: shopyo-settings==1.2.0
Requires-Dist: shopyo-theme==1.1.0
Dynamic: author
Dynamic: author-email
Dynamic: classifier
Dynamic: description
Dynamic: description-content-type
Dynamic: keywords
Dynamic: project-url
Dynamic: requires-dist
Dynamic: requires-python
